<TextReading>
	<slideInfo>
		<hText>Mrs. Beeton’s Book of Household Management</hText>
		<image></image>
		<audio>audio/euro_m2-4_s12.mp3</audio>
		<mainText><![CDATA[<p>Menus<br />DINNER FOR 12 PERSONS (May)<br />
FIRST COURSE.<br />White Soup<br />Asparagus Soup<br />Salmon Cutlets, Boiled Turbot, and Lobster Sauce<br />
ENTREES.<br />Chicken Vol-au-Vent<br />Lamb Cutlets and Cucumbers<br />Fricandeau of Veal<br />Stewed Mushrooms<br />
SECOND COURSE.<br />Roast Lamb, Haunch of Mutton<br />Boiled and Roast Fowls<br />Vegetables<br />
THIRD COURSE.<br />Ducklings<br />Goslings<br />Charlotte Russe<br />Vanilla Cream<br />Gooseberry Tart, Custards<br />Cheesecakes<br />Cabinet Pudding and Iced Pudding<br />Deserts and Ices<br /><br />
PLAIN FAMILY DINNERS FOR MAY<br />
<font face='lc-Italic'>Sunday</font>—1. Vegetable soup. 2. Saddle of mutton, asparagus and potatoes. 3. Gooseberry tart.<br />
<font face='lc-Italic'>Monday</font>—1. Fried whitings, anchovy sauce. 2. Cold mutton, mashed potatoes, stewed veal. 3. Fig pudding.<br />
<font face='lc-Italic'>Tuesday</font>—1. Haricot mutton, made from remains of cold mutton, rump-steak pie. 2. Macaroni<br />
<font face='lc-Italic'>Wednesday</font>—1. Roast loin of veal and spinach, boiled bacon, mutton cutlets and tomato sauce. 2. Gooseberry pudding and cream.<br />
<font face='lc-Italic'>Thursday</font>—1. Spring soup. 2. Roast leg of lamb, mint sauce, spinach curried veal and rice. 3. Lemon pudding<br />
<font face='lc-Italic'>Friday</font>—1. Boiled mackerel and parsley-and-butter. 2. Stewed rump-steak, cold lamb and salad. 3. Baked gooseberry pudding<br />
<font face='lc-Italic'>Saturday</font>—1. Vermicelli. 2. Rump-steak pudding, lamb cutlets, and cucumbers. 3. Macaroni</p>]]></mainText>
	</slideInfo>	
</TextReading>